jupy_sqlite_extension/__init__.py
jupy_sqlite_extension/_version.py
jupy_sqlite_extension/handlers.py
jupy_sqlite_extension/labextension/build_log.json
jupy_sqlite_extension/labextension/package.json
jupy_sqlite_extension/labextension/static/lib_index_js.c7336a689a0c7c3ba9fb.js
jupy_sqlite_extension/labextension/static/lib_index_js.c7336a689a0c7c3ba9fb.js.map
jupy_sqlite_extension/labextension/static/remoteEntry.494b8bea1d5745e4d0fe.js
jupy_sqlite_extension/labextension/static/remoteEntry.494b8bea1d5745e4d0fe.js.map
jupy_sqlite_extension/labextension/static/style.js
jupy_sqlite_extension/labextension/static/style_index_js.3662c0021598ff75b46d.js
jupy_sqlite_extension/labextension/static/style_index_js.3662c0021598ff75b46d.js.map
jupy_sqlite_extension/tests/__init__.py
jupy_sqlite_extension/tests/test_handlers.py
jupy_sqlite_extension-0.1.1.data/data/etc/jupyter/jupyter_server_config.d/jupy_sqlite_extension.json
jupy_sqlite_extension-0.1.1.data/data/share/jupyter/labextensions/jupy-sqlite-extension/build_log.json
jupy_sqlite_extension-0.1.1.data/data/share/jupyter/labextensions/jupy-sqlite-extension/package.json
jupy_sqlite_extension-0.1.1.data/data/share/jupyter/labextensions/jupy-sqlite-extension/static/lib_index_js.c7336a689a0c7c3ba9fb.js
jupy_sqlite_extension-0.1.1.data/data/share/jupyter/labextensions/jupy-sqlite-extension/static/lib_index_js.c7336a689a0c7c3ba9fb.js.map
jupy_sqlite_extension-0.1.1.data/data/share/jupyter/labextensions/jupy-sqlite-extension/static/remoteEntry.494b8bea1d5745e4d0fe.js
jupy_sqlite_extension-0.1.1.data/data/share/jupyter/labextensions/jupy-sqlite-extension/static/remoteEntry.494b8bea1d5745e4d0fe.js.map
jupy_sqlite_extension-0.1.1.data/data/share/jupyter/labextensions/jupy-sqlite-extension/static/style.js
jupy_sqlite_extension-0.1.1.data/data/share/jupyter/labextensions/jupy-sqlite-extension/static/style_index_js.3662c0021598ff75b46d.js
jupy_sqlite_extension-0.1.1.dist-info/METADATA
jupy_sqlite_extension-0.1.1.dist-info/WHEEL
jupy_sqlite_extension-0.1.1.dist-info/licenses/LICENSE
jupy_sqlite_extension-0.1.1.dist-info/RECORD
